ares_util/__init__.py
ares_util/ares.py
ares_util/exceptions.py
ares_util/helpers.py
ares_util/settings.py
ares_util/validators.py
ares_util-0.3.0.dist-info/AUTHORS
ares_util-0.3.0.dist-info/LICENSE
ares_util-0.3.0.dist-info/METADATA
ares_util-0.3.0.dist-info/WHEEL
ares_util-0.3.0.dist-info/top_level.txt
ares_util-0.3.0.dist-info/zip-safe
ares_util-0.3.0.dist-info/RECORD
